<?xml version="1.0" encoding="UTF-8" standalone="no"?>
<window xmlns="http://jmix.io/schema/ui/window"
        caption="msg://carWithModelEdit.caption"
        focusComponent="form">
    <data>
        <instance id="carWithModelDc"
                  class="com.company.storedprocedures.entity.CarWithModel"/>
    </data>
    <facets>
        <dataLoadCoordinator auto="true"/>
        <screenSettings id="settingsFacet" auto="true"/>
    </facets>
    <actions>
        <action id="windowCommitAndClose" caption="msg:///actions.Ok"
                icon="EDITOR_OK"
                primary="true"
                shortcut="${COMMIT_SHORTCUT}"/>
        <action id="windowClose"
                caption="msg:///actions.Close"
                icon="EDITOR_CANCEL"/>
    </actions>
    <dialogMode height="600"
                width="800"/>
    <layout spacing="true" expand="editActions">
        <form id="form" dataContainer="carWithModelDc">
            <column width="350px">
                <textField id="vinField" property="vin" editable="false"/>
                <textField id="yearField" property="year">
                    <formatter>
                        <number format="#"/>
                    </formatter>
                </textField>
                <textField id="modelField" property="model" editable="false"/>
            </column>
        </form>
        <hbox id="editActions" spacing="true">
            <button id="commitAndCloseBtn" action="windowCommitAndClose"/>
            <button id="closeBtn" action="windowClose"/>
        </hbox>
    </layout>
</window>